jinja2_easy/generator.py
jinja2_easy_generator-0.0.3.dist-info/LICENSE
jinja2_easy_generator-0.0.3.dist-info/METADATA
jinja2_easy_generator-0.0.3.dist-info/WHEEL
jinja2_easy_generator-0.0.3.dist-info/top_level.txt
jinja2_easy_generator-0.0.3.dist-info/RECORD
